[{"keyword":"활발하다","count":4},{"keyword":"평화롭다","count":26},{"keyword":"기분좋다","count":15},{"keyword":"평온하다","count":15},{"keyword":"놀랍다","count":4},{"keyword":"부담스럽다","count":4},{"keyword":"활기차다","count":15},{"keyword":"마음이열린다","count":4},{"keyword":"쾌활하다","count":4},{"keyword":"캄캄하다","count":4},{"keyword":"흥겹다","count":37},{"keyword":"관대하다","count":15},{"keyword":"유쾌하다","count":37},{"keyword":"쓰리다","count":4},{"keyword":"귀찮다","count":4},{"keyword":"시원하다","count":15},{"keyword":"놀라다","count":4},{"keyword":"그립다","count":4},{"keyword":"자신감을느낀다","count":4},{"keyword":"무섭다","count":4},{"keyword":"생기있다","count":15},{"keyword":"자유롭다","count":4},{"keyword":"소름끼치다","count":4},{"keyword":"편안하다","count":48},{"keyword":"좋다","count":26},{"keyword":"개운하다","count":4},{"keyword":"불안하다","count":4},{"keyword":"겁에질리다","count":15},{"keyword":"상큼하다","count":4},{"keyword":"골치아프다","count":4},{"keyword":"훈훈하다","count":4},{"keyword":"멋있다","count":15},{"keyword":"자유스럽다","count":26},{"keyword":"구역질이나다","count":4},{"keyword":"처참하다","count":4},{"keyword":"든든하다","count":4},{"keyword":"산뜻하다","count":15},{"keyword":"구역질이난다","count":4},{"keyword":"마음이넓다","count":15},{"keyword":"당당하다","count":4},{"keyword":"짜릿하다","count":4},{"keyword":"긴장을느낀다","count":15},{"keyword":"어이없다","count":4},{"keyword":"보기좋다","count":15},{"keyword":"의기양양하다","count":4},{"keyword":"안전하다","count":15}]